ws/prometheus_uptimerobot/__init__.py
ws/prometheus_uptimerobot/web.py
ws/prometheus_uptimerobot/tests/__init__.py
ws/prometheus_uptimerobot/tests/response.json
ws/prometheus_uptimerobot/tests/test_web.py
ws.prometheus_uptimerobot-1.3.0.dist-info/METADATA
ws.prometheus_uptimerobot-1.3.0.dist-info/WHEEL
ws.prometheus_uptimerobot-1.3.0.dist-info/entry_points.txt
ws.prometheus_uptimerobot-1.3.0.dist-info/RECORD
