Metadata-Version: 2.1
Name: ws.prometheus_uptimerobot
Version: 1.3.0
Summary: Export uptimerobot.com monitor results as prometheus.io metrics
Project-URL: Repository, https://github.com/wosc/prometheus-uptimerobot
Author-email: Wolfgang Schnerring <wosc@wosc.de>
License:  BSD-3-Clause
Requires-Python: >=3.7
Requires-Dist: prometheus-client
Requires-Dist: requests
Provides-Extra: test
Requires-Dist: pytest; extra == 'test'
Requires-Dist: pytest-cov; extra == 'test'
Requires-Dist: setuptools; extra == 'test'
Requires-Dist: werkzeug; extra == 'test'
